dataqueryanalyze/__init__.py
dataqueryanalyze/app.so
dataqueryanalyze/load.py
dataqueryanalyze/core/auto.so
dataqueryanalyze/core/data_clean.so
dataqueryanalyze/core/data_res.so
dataqueryanalyze/core/draw.so
dataqueryanalyze/core/funtions.so
dataqueryanalyze/core/hlp.so
dataqueryanalyze/core/llm.so
dataqueryanalyze/core/sql.so
dataqueryanalyze/core/task_manager.so
dataqueryanalyze/extensions/sample_extension.py
dataqueryanalyze-1.6.3.dist-info/licenses/LICENSE
dataqueryanalyze-1.6.3.dist-info/METADATA
dataqueryanalyze-1.6.3.dist-info/WHEEL
dataqueryanalyze-1.6.3.dist-info/entry_points.txt
dataqueryanalyze-1.6.3.dist-info/top_level.txt
dataqueryanalyze-1.6.3.dist-info/RECORD
