Metadata-Version: 2.4
Name: dataqueryanalyze
Version: 1.6.3
Summary: 一个基于Polars和DuckDB的高效数据查析工具
Home-page: 
Author: Randy
Author-email: Randy <411703730@qq.com>
License: 专有软件许可证协议
Platform: manylinux2014_x86_64
Classifier: Programming Language :: Python :: 3
Classifier: Programming Language :: Python :: 3.8
Classifier: Programming Language :: Python :: 3.9
Classifier: Programming Language :: Python :: 3.10
Classifier: Programming Language :: Python :: 3.11
Classifier: Programming Language :: Python :: 3.12
Classifier: Programming Language :: Python :: 3.13
Classifier: Programming Language :: Python :: 3.14
Classifier: License :: Other/Proprietary License
Classifier: Operating System :: POSIX :: Linux
Classifier: Intended Audience :: Developers
Classifier: Intended Audience :: Science/Research
Classifier: Topic :: Scientific/Engineering :: Information Analysis
Classifier: Topic :: Software Development :: Libraries :: Python Modules
Requires-Python: >=3.8,<3.15
License-File: LICENSE
Requires-Dist: PySide6>=5.0.0
Requires-Dist: polars>=0.20.0
Requires-Dist: duckdb>=0.10.0
Requires-Dist: matplotlib>=3.0.0
Requires-Dist: requests>=2.0.0
Requires-Dist: numpy>=1.0.0
Requires-Dist: packaging>=20.0
Requires-Dist: pycryptodome>=3.0.0
Requires-Dist: fastexcel>=0.0.1
Requires-Dist: pyarrow>=0.0.1
Dynamic: author
Dynamic: license-file
Dynamic: requires-python
